daenerys/__init__.py
daenerys/app.py
daenerys/dinergate.py
daenerys/exceptions.py
daenerys/request.py
daenerys/site.py
daenerys/pipeline/__init__.py
daenerys/pipeline/base.py
daenerys/pipeline/html.py
daenerys/pipeline/network.py
daenerys-0.1.dist-info/METADATA
daenerys-0.1.dist-info/RECORD
daenerys-0.1.dist-info/WHEEL
daenerys-0.1.dist-info/top_level.txt
