Metadata-Version: 2.1
Name: daenerys
Version: 0.1
Summary: Scraping and Web Crawling Framework
Home-page: https://code.pycourses.com/courses/daenerys
Author: Dong Weiming
Author-email: 61966225@qq.com
License: UNKNOWN
Platform: UNKNOWN
Classifier: Development Status :: 4 - Beta
Classifier: Intended Audience :: Developers
Classifier: Operating System :: OS Independent
Classifier: Programming Language :: Python
Classifier: Programming Language :: Python :: 2
Classifier: Programming Language :: Python :: 3
Classifier: Programming Language :: Python :: 3.6
Classifier: Programming Language :: Python :: Implementation :: CPython
Classifier: Programming Language :: Python :: Implementation :: PyPy
